gokunemu/__init__.py
gokunemu/input_limits-W.txt
gokunemu/mfbox.py
gokunemu/pplusf_0195.npy
gokunemu/train_model.py
gokunemu/models/L1A/best_model.pth
gokunemu/models/L1HAr/best_model.pth
gokunemu/models/L2/best_model.pth
gokunemu/models/L2Hr/best_model.pth
gokunemu/models/L2_linear/best_model.pth
gokunemu/models/L2_retrain_1_local/best_model.pth
gokunemu/models/L2_retrain_local/best_model.pth
gokunemu-0.1.8.dist-info/licenses/LICENSE
gokunemu-0.1.8.dist-info/METADATA
gokunemu-0.1.8.dist-info/WHEEL
gokunemu-0.1.8.dist-info/top_level.txt
gokunemu-0.1.8.dist-info/RECORD
